PyBetween/APIHandler.py
PyBetween/PyBetween.py
PyBetween/__init__.py
PyBetween-1.0.3.dist-info/LICENSE
PyBetween-1.0.3.dist-info/METADATA
PyBetween-1.0.3.dist-info/WHEEL
PyBetween-1.0.3.dist-info/top_level.txt
PyBetween-1.0.3.dist-info/RECORD
