Metadata-Version: 2.1
Name: PyBetween
Version: 1.0.3
Summary: Python wrapper for Between app
Home-page: https://github.com/lill74/PyBetween
Author: lill74
Author-email: a010393223@gmail.com
License: MIT
Platform: UNKNOWN
License-File: LICENSE
